README.rst
setup.py
django_online.egg-info/PKG-INFO
django_online.egg-info/SOURCES.txt
django_online.egg-info/dependency_links.txt
django_online.egg-info/not-zip-safe
django_online.egg-info/top_level.txt
online/__init__.py
online/backend.py
online/compat.py
online/middleware.py
online/models.py
online/settings.py
online/tests/__init__.py
online/tests/models.py
online/tests/settings.py
online/tests/tests.py
online/tests/urls.py
online/tests/views.py